vectorize_client/__init__.py
vectorize_client/api/__init__.py
vectorize_client/api/ai_platform_connectors_api.py
vectorize_client/api/destination_connectors_api.py
vectorize_client/api/extraction_api.py
vectorize_client/api/files_api.py
vectorize_client/api/pipelines_api.py
vectorize_client/api/source_connectors_api.py
vectorize_client/api/uploads_api.py
vectorize_client/api/workspaces_api.py
vectorize_client/api_client.py
vectorize_client/api_response.py
vectorize_client/configuration.py
vectorize_client/exceptions.py
vectorize_client/models/__init__.py
vectorize_client/models/add_user_from_source_connector_response.py
vectorize_client/models/add_user_to_source_connector_request.py
vectorize_client/models/add_user_to_source_connector_request_selected_files.py
vectorize_client/models/add_user_to_source_connector_request_selected_files_any_of.py
vectorize_client/models/add_user_to_source_connector_request_selected_files_any_of_value.py
vectorize_client/models/advanced_query.py
vectorize_client/models/ai_platform_config_schema.py
vectorize_client/models/ai_platform_connector.py
vectorize_client/models/ai_platform_connector_input.py
vectorize_client/models/ai_platform_connector_type.py
vectorize_client/models/ai_platform_type_for_pipeline.py
vectorize_client/models/anthropic.py
vectorize_client/models/anthropic1.py
vectorize_client/models/anthropic_auth_config.py
vectorize_client/models/aws_s3.py
vectorize_client/models/aws_s31.py
vectorize_client/models/awss3_auth_config.py
vectorize_client/models/awss3_config.py
vectorize_client/models/azure_blob.py
vectorize_client/models/azure_blob1.py
vectorize_client/models/azureaisearch.py
vectorize_client/models/azureaisearch1.py
vectorize_client/models/azureaisearch_auth_config.py
vectorize_client/models/azureaisearch_config.py
vectorize_client/models/azureblob_auth_config.py
vectorize_client/models/azureblob_config.py
vectorize_client/models/bedrock.py
vectorize_client/models/bedrock1.py
vectorize_client-0.4.0.dist-info/METADATA
vectorize_client-0.4.0.dist-info/WHEEL
vectorize_client-0.4.0.dist-info/RECORD
