Metadata-Version: 2.1
Name: vectorize-client
Version: 0.4.0
Summary: Python client for the Vectorize API
Home-page: https://vectorize.io
License: MIT
Keywords: vectorize,vectorize.io,generative-ai,embeddings,rag
Author: Vectorize
Author-email: contact@vectorize.io
Requires-Python: >=3.8,<4.0
Classifier: License :: OSI Approved :: MIT License
Classifier: Programming Language :: Python :: 3
Classifier: Programming Language :: Python :: 3.8
Classifier: Programming Language :: Python :: 3.9
Classifier: Programming Language :: Python :: 3.10
Classifier: Programming Language :: Python :: 3.11
Classifier: Programming Language :: Python :: 3.12
Requires-Dist: pydantic (>=2)
Requires-Dist: python-dateutil (>=2.8.2)
Requires-Dist: typing-extensions (>=4.7.1)
Requires-Dist: urllib3 (>=1.25.3,<3.0.0)
Project-URL: Repository, https://github.com/vectorize-io/vectorize-clients
